flask_pw/__init__.py
flask_pw/debugtoolbar.py
flask_pw/models.py
Flask_PW_2020-1.1.3.dist-info/AUTHORS.rst
Flask_PW_2020-1.1.3.dist-info/LICENSE
Flask_PW_2020-1.1.3.dist-info/METADATA
Flask_PW_2020-1.1.3.dist-info/WHEEL
Flask_PW_2020-1.1.3.dist-info/top_level.txt
Flask_PW_2020-1.1.3.dist-info/RECORD
