Metadata-Version: 2.1
Name: Flask-PW-2020
Version: 1.1.3
Summary: Peewee ORM integration for Flask framework
Home-page: https://github.com/rightplace/rp-flask-pw
Author: Kirill Klenov
Author-email: horneds@gmail.com
License: MIT
Keywords: flask,peewee,migrations,migrate,signals
Platform: Any
Classifier: Development Status :: 4 - Beta
Classifier: Intended Audience :: Developers
Classifier: License :: OSI Approved :: BSD License
Classifier: Natural Language :: English
Classifier: Natural Language :: Russian
Classifier: Operating System :: OS Independent
Classifier: Programming Language :: Python :: 2
Classifier: Programming Language :: Python :: 3
Classifier: Programming Language :: Python
Classifier: Topic :: Software Development :: Libraries :: Python Modules
Classifier: Topic :: Software Development :: Testing
Classifier: Topic :: Utilities
Requires-Dist: Flask (>=0.11.1)
Requires-Dist: peewee-migrate (>=0.9.3)
